Toolbox/__init__.py
Toolbox/toolbox.py
Toolbox/classes/__init__.py
Toolbox/classes/dashboard.py
Toolbox/classes/import_data.py
Toolbox/classes/model_analysis.py
Toolbox/classes/reformate_fao_data.py
Toolbox/classes/scenario_plots.py
Toolbox/classes/utils.py
Toolbox/cli/__init__.py
Toolbox/cli/cli.py
Toolbox/pages/__init__.py
Toolbox/pages/forest_db.py
Toolbox/pages/overview_db.py
Toolbox/pages/price_db.py
Toolbox/pages/trade_db.py
Toolbox/pages/validation_db.py
Toolbox/parameters/default_parameters.py
Toolbox/parameters/defines.py
Toolbox/parameters/defines_geo.py
Toolbox/parameters/paths.py
timba_charts-0.3.3.dist-info/licenses/COPYING
timba_charts-0.3.3.dist-info/METADATA
timba_charts-0.3.3.dist-info/WHEEL
timba_charts-0.3.3.dist-info/entry_points.txt
timba_charts-0.3.3.dist-info/top_level.txt
timba_charts-0.3.3.dist-info/RECORD
