Metadata-Version: 2.4
Name: TiMBA_Charts
Version: 0.3.3
Summary: A toolbox for analysing forest sector model results.
License-Expression: AGPL-3.0-or-later
Project-URL: Repository, https://github.com/TI-Forest-Sector-Modelling/TiMBA_Charts
Classifier: Programming Language :: Python :: 3
Classifier: Operating System :: Microsoft :: Windows
Classifier: Intended Audience :: Science/Research
Requires-Python: >=3.9
License-File: COPYING
Requires-Dist: click==8.1.7
Requires-Dist: numpy==1.26.4
Requires-Dist: pandas==1.5.3
Requires-Dist: dash==3.0.0
Requires-Dist: dash-bootstrap-components==2.0.0
Requires-Dist: seaborn==0.13.2
Provides-Extra: dev
Requires-Dist: pytest==8.3.5; extra == "dev"
Requires-Dist: pytest-cov==6.2.1; extra == "dev"
Dynamic: license-file
